jericho/__init__.py
jericho/clubfloyd_verb_counts.json
jericho/defines.py
jericho/game_info.py
jericho/jericho.py
jericho/libfrotz.so
jericho/template_action_generator.py
jericho/util.py
jericho/version.py
jericho-3.2.0.dist-info/LICENSE
jericho-3.2.0.dist-info/METADATA
jericho-3.2.0.dist-info/WHEEL
jericho-3.2.0.dist-info/top_level.txt
jericho-3.2.0.dist-info/RECORD
